korea_geocoder_mcp/__init__.py
korea_geocoder_mcp/geocoder.py
korea_geocoder_mcp-0.1.0.dist-info/METADATA
korea_geocoder_mcp-0.1.0.dist-info/WHEEL
korea_geocoder_mcp-0.1.0.dist-info/entry_points.txt
korea_geocoder_mcp-0.1.0.dist-info/licenses/LICENSE
korea_geocoder_mcp-0.1.0.dist-info/RECORD
