Metadata-Version: 2.4
Name: korea-geocoder-mcp
Version: 0.1.0
Summary: A Model Context Protocol (MCP) server for geocoding Korean addresses using Google Maps API
Project-URL: Homepage, https://github.com/wowzoo/korea-geocoder-mcp
Project-URL: Repository, https://github.com/wowzoo/korea-geocoder-mcp
Project-URL: Issues, https://github.com/wowzoo/korea-geocoder-mcp/issues
Author-email: wowzoo <wowzoo@gmail.com>
License: MIT License
License-File: LICENSE
Keywords: address,coordinates,geocoding,korea,mcp
Classifier: Development Status :: 4 - Beta
Classifier: Intended Audience :: Developers
Classifier: License :: OSI Approved :: MIT License
Classifier: Operating System :: OS Independent
Classifier: Programming Language :: Python :: 3
Classifier: Programming Language :: Python :: 3.10
Classifier: Programming Language :: Python :: 3.11
Classifier: Programming Language :: Python :: 3.12
Classifier: Programming Language :: Python :: 3.13
Classifier: Topic :: Scientific/Engineering :: GIS
Classifier: Topic :: Software Development :: Libraries :: Python Modules
Requires-Python: >=3.10
Requires-Dist: fastmcp>=2.10.1
Requires-Dist: googlemaps>=4.10.0
Requires-Dist: requests>=2.32.4
